.bzrignore
COPYING
ChangeLog
INSTALL.txt
Makefile
README.txt
TODO.txt
setup.cfg
setup.py
docs/Makefile
docs/overview.txt
softwarefabrica/__init__.py
softwarefabrica.django.director.egg-info/PKG-INFO
softwarefabrica.django.director.egg-info/SOURCES.txt
softwarefabrica.django.director.egg-info/dependency_links.txt
softwarefabrica.django.director.egg-info/namespace_packages.txt
softwarefabrica.django.director.egg-info/not-zip-safe
softwarefabrica.django.director.egg-info/requires.txt
softwarefabrica.django.director.egg-info/top_level.txt
softwarefabrica/django/__init__.py
softwarefabrica/django/director/__init__.py
softwarefabrica/django/director/bzrcachedrev.py
softwarefabrica/django/director/finddata.py
softwarefabrica/django/director/modelmanager.py
softwarefabrica/django/director/models.py
softwarefabrica/django/director/tests.py
softwarefabrica/django/director/version.py
softwarefabrica/django/director/views.py
softwarefabrica/django/director/templates/director/tags/apps_menu.html
softwarefabrica/django/director/templatetags/__init__.py
softwarefabrica/django/director/templatetags/directortags.py