Metadata-Version: 1.0
Name: softwarefabrica.django.director
Version: 0.9dev-BZR-r1-panta-elasticworld.org-20110427165731-j00nsiss2af57yhu
Summary: Advanced model manager for SoftwareFabrica django projects
Home-page: http://cheeseshop.python.org/pypi/softwarefabrica.django.director/
Author: Marco Pantaleoni
Author-email: m.pantaleoni@softwarefabrica.org
License: GNU GPL v2
Download-URL: http://pypi.python.org/packages/source/s/softwarefabrica.django.director/softwarefabrica.django.director-0.9dev-BZR-r1-panta-elasticworld.org-20110427165731-j00nsiss2af57yhu.tar.gz
Keywords: director model manager infrastructure django softwarefabrica
Platform: UNKNOWN
Classifier: Development Status :: 4 - Beta
Classifier: Framework :: Django
Classifier: Intended Audience :: Developers
Classifier: License :: OSI Approved :: GNU General Public License (GPL)
Classifier: Operating System :: OS Independent
Classifier: Programming Language :: Python :: 2.5
Classifier: Topic :: Software Development :: Libraries :: Python Modules
